jixin/__init__.py
Jixin-1.0.0.dist-info/METADATA
Jixin-1.0.0.dist-info/WHEEL
Jixin-1.0.0.dist-info/top_level.txt
Jixin-1.0.0.dist-info/RECORD
