Metadata-Version: 2.1
Name: Jixin
Version: 1.0.0
Summary: JSON (de)serialization mix-ins.
Home-page: https://github.com/afaulconbridge/jixin
Author: Adam Faulconbridge
Author-email: afaulconbridge@googlemail.com
License: LICENSE.txt
Platform: UNKNOWN
Classifier: Programming Language :: Python :: 3
Classifier: License :: OSI Approved :: MIT License
Classifier: Operating System :: OS Independent
Provides-Extra: dev
Requires-Dist: pytest-cov ; extra == 'dev'
Requires-Dist: flake8 ; extra == 'dev'
Requires-Dist: black ; extra == 'dev'
Requires-Dist: pylint ; extra == 'dev'
Requires-Dist: pip-tools ; extra == 'dev'
Requires-Dist: pipdeptree ; extra == 'dev'
Requires-Dist: pre-commit ; extra == 'dev'
